{
    "default_chat_settings": {
        "default_quiz_type": "session",
        "default_num_questions": 10,
        "default_open_period_seconds": 30,
        "default_announce_quiz": false,
        "default_announce_delay_seconds": 30,
        "enabled_categories": null,
        "disabled_categories": [],
        "num_categories_per_quiz": 3,
        "quiz_categories_mode": "all",
        "quiz_categories_pool": [],
        "daily_quiz": {
            "enabled": false,
            "times_msk": [
                {
                    "hour": 7,
                    "minute": 0
                }
            ],
            "categories_mode": "random",
            "num_random_categories": 3,
            "specific_categories": [],
            "num_questions": 10,
            "interval_seconds": 60,
            "poll_open_seconds": 600
        },
        "auto_delete_bot_messages": true,
        "default_interval_seconds": 30,
        "quiz_settings": {
            "default_categories_mode": "all",
            "default_num_random_categories": 3,
            "default_specific_categories": [],
            "default_interval_seconds": 30,
            "default_open_period_seconds": 30,
            "default_announce_quiz": false,
            "default_announce_delay_seconds": 5
        }
    },
    "quiz_types_config": {
        "single": {
            "type": "single",
            "mode": "single_question",
            "default_num_questions": 1,
            "default_open_period_seconds": 30,
            "announce": false,
            "announce_delay_seconds": 0
        },
        "session": {
            "type": "session",
            "mode": "serial_immediate",
            "default_num_questions": 10,
            "default_open_period_seconds": 30,
            "default_interval_seconds": 30,
            "announce": false,
            "announce_delay_seconds": 30
        },
        "daily": {
            "type": "daily",
            "mode": "serial_interval",
            "default_num_questions": 10,
            "default_open_period_seconds": 600,
            "default_interval_seconds": 60,
            "announce": true,
            "announce_delay_seconds": 0,
            "default_categories_mode": "random",
            "default_num_random_categories": 3,
            "default_specific_categories": [],
            "default_times_msk": [
                {
                    "hour": 7,
                    "minute": 0
                }
            ],
            "enabled": false
        }
    },
    "global_settings": {
        "commands": {
            "start": "start",
            "help": "help",
            "quiz": "quiz",
            "categories": "categories",
            "top": "top",
            "global_top": "globaltop",
            "mystats": "mystats",
            "stop_quiz": "stopquiz",
            "cancel": "cancel",
            "admin_settings": "adminsettings",
            "reset_categories_stats": "reset_categories_stats",
            "chat_stats": "chat_stats",
            "category_stats": "category_stats",
            "chatcategories": "chatcategories"
        },
        "developer_notifications": {
            "enabled": true,
            "developer_user_id": 621817842,
            "notify_on_malformed_questions": true,
            "notify_on_data_errors": true,
            "notify_on_system_errors": false
        },
        "max_questions_per_session": 50,
        "max_interactive_categories_to_show": 10,
        "job_grace_period_seconds": 3,
        "max_poll_question_length": 280,
        "max_poll_option_length": 90,
        "explanation_max_length": 200,
        "chat_achievements": {
            "-100": "💀 {user_name}, ты блин издеваешься, такое не возможно вообще! Попробуй не вытворять больше!",
            "-50": "😵 {user_name}, ну и нуб, прям с порога падает... Поправься уже!",
            "-25": "⚰️ {user_name}, это уже эпично... {user_score} очков. Нужен герой!",
            "-20": "🤦‍♂️ {user_name}, опять промах? Кажется, тебе пора на тренировку.",
            "-10": "🙃 {user_name}, ну ничего, даже у профессионалов бывают плохие дни... правда?",
            "-5": "😔 {user_name}, не везет... У тебя {user_score} очков. Не сдавайся!",
            "0": "😐 {user_name}, нейтральная территория. {user_score} очков. Время действовать!",
            "15": "🎯 {user_name} первый шаг! 15 очков — начало пути!",
            "30": "🔥 {user_name} разогревается и зажигает чат! 30 очков!",
            "50": "🌟 {user_name} - легенда чата! {user_score} очков!",
            "75": "⚡ {user_name} повышает уровень — 75 очков в кармане!",
            "100": "💎 {user_name} - бриллиант чата! {user_score} очков!",
            "125": "🏅 {user_name} уверенно входит в топ — 125 очков!",
            "175": "🚀 Ускорение началось! {user_name} пробил рубеж — 175 очков!",
            "225": "💎 {user_name} словно самоцвет — 225 очков!",
            "250": "💎 Ого ого! {user_name} набрал {user_score} очков!",
            "300": "💎 {user_name} набрал 300 очков! Ты настоящий алмаз в нашем сообществе!",
            "350": "🪐 {user_name} полёт на орбиту знаний — 350 очков!",
            "500": "🏆 {user_name} набрал 500 очков! Настоящий чемпион!",
            "600": "👑 {user_name} новый БОСС викторины! 600 очков — вершина земного уровня!",
            "750": "🌈 {user_name} набрал 750 очков! Дал дал ушёл!",
            "800": "🌈 {user_name} переступает грань возможного — 800 очков!",
            "1000": "✨ {user_name} набрал 1000 очков! Ты легенда!",
            "1200": "✨ {user_name} — легенда вне понимания! 1200 очков!",
            "1500": "🔥 {user_name} набрал 1500 очков! Огонь неистощимой энергии!",
            "1700": "🌋🔥 {user_name} взрывается, как суперновая звезда! 1700 очков!",
            "2000": "🚀 {user_name} набрал 2000 очков! Сверхзвездный уровень!",
            "2200": "🌀 {user_name} достиг(ла) вихря космического сознания! 2200 очков!",
            "2500": "⚔️ {user_name} набрал 2500 очков! Персонаж мифов и легенд!",
            "2700": "⚔️ {user_name} теперь персонаж мифов и легенд! 2700 очков!",
            "3000": "👑 {user_name} набрал 3000 очков! Царь и бог знаний!",
            "3200": "👾 {user_name} властвует над мультивселенной знаний! 3200 очков!",
            "3500": "🌌 {user_name} набрал 3500 очков! Космический уровень!",
            "3700": "🌌⚡ {user_name} разрывает пространство и время! 3700 очков!",
            "4000": "🌟 {user_name} набрал 4000 очков! Звездный уровень!",
            "4200": "⛩️ {user_name} вошёл(ла) в ранг божества всезнания! 4200 очков!",
            "4500": "💫 {user_name} набрал 4500 очков! Божественный уровень!",
            "4700": "🧬 {user_name} переписал(а) ДНК самой викторины! 4700 очков!",
            "5000": "💥 {user_name} набрал 5000 очков! Э-э-это ты создатель вселенной?!",
            "5200": "💀🚫 ВСЁ, {user_name} СЛОМАЛ(А) СИСТЕМУ! 5200 очков!",
            "5500": "🌌 {user_name} набрал 5500 очков! За пределами понимания!",
            "6000": "💎✨ {user_name} достиг абсолютного совершенства! 6000 очков! Конец игры!",
            "5": "🎯 {user_name} начинает свой путь в этом чате! {user_score} очков!",
            "10": "🔥 {user_name} разогревается! {user_score} очков в чате!",
            "25": "👑 {user_name} - король этого чата! {user_score} очков!",
            "150": "🏅 {user_name} уверенно входит в топ — 150 очков!"
        },
        "rating_display_limit": 10,
        "max_daily_quiz_times_per_chat": 5,
        "streak_achievements": {
            "5": "📘 Отличный старт! {user_name} собрал(а) серию из {streak} верных ответов!",
            "7": "🔎 Внимательность на высоте! {user_name} держит уже {streak} подряд!",
            "10": "🎓 Первое серьёзное достижение! {user_name} ответил(а) верно {streak} раз подряд!",
            "12": "🧩 Серия разгаданных загадок! {user_name} набрал(а) {streak} подряд!",
            "15": "🔮 {user_name} словно ясновидящий! {streak} правильных подряд!",
            "18": "⚖️ Баланс знаний сохранён — {user_name} держит {streak} подряд!",
            "20": "🌟 {user_name} вошёл(ла) в зал славы викторины — {streak} подряд!",
            "25": "🛰️ Границы реальности раздвинуты: {user_name} уже {streak} подряд!",
            "30": "📡 Космическая точность! {user_name} дал(а) {streak} верных подряд!",
            "35": "🧙 {user_name} стал(а) мудрецом викторины — {streak} подряд!",
            "40": "🌌 {user_name} достиг(ла) звёздного уровня знаний — {streak} подряд!",
            "45": "🏛️ Исторический рекорд! {user_name} держит {streak} подряд!",
            "50": "♾️ {user_name} переписал(а) правила викторины! {streak} подряд — выше уже немыслимо!",
            "3": "🔥 {user_name} набирает обороты! Серия из {streak} правильных ответов!",
            "streak_achievements": {
                "3": "🔊 В ритме! {user_name} ловит кураж и собирает серию из {streak} правильных ответов!",
                "5": "📈 Импульс нарастает! {user_name} уверенно держит серию из {streak} попаданий!",
                "7": "🔎 Детали имеют значение! Ничто не ускользает от взора {user_name} уже {streak} вопросов подряд!",
                "10": "🎯 Без промаха! Цепочка из {streak} верных ответов — {user_name} в ударе!",
                "12": "🧠 Включён режим «Мозговой штурм»! {user_name} выдаёт ответы вот уже {streak} раз кряду!",
                "15": "🔥 Накал страстей! {user_name} вошёл(а) в состояние потока и не собирается сбавлять темп ({streak})!",
                "18": "⚖️ Идеальный баланс знаний и удачи! {user_name} держит серию из {streak} правильных ответов!",
                "20": "🏆 Рекордный рывок! Целых {streak} верных ответов подряд — {user_name}, ты в зале славы!",
                "25": "🚀 Отрыв от реальности! С такой серией ({streak}) {user_name} уже на подлёте к Марсу!",
                "30": "🤯 У нас тут горит! Проверьте, всё ли в порядке с {user_name} после {streak} правильных ответов подряд!",
                "35": "🧙 С точки зрения магии... {user_name} совершил(а) {streak} магических попаданий!",
                "40": "🌠 Загадайте желание! Падающая звезда по имени {user_name} только что поймала серию в {streak} очков!",
                "45": "🏛️ Имя {user_name} и его(её) серия из {streak} ответов высечены в мраморе истории!",
                "50": "♾️ Абсолют! {user_name} достиг(ла) дзена и воплотил(а) его в серию из {streak} правильных ответов!"
            }
        },
        "streak_bonuses": {
            "enabled": true,
            "base_multiplier": 0.2,
            "max_multiplier": 3.0,
            "min_streak_for_bonus": 5
        },
        "support_contact": "@Ilzrd"
    }
}